psychopy_crs/__init__.py
psychopy_crs/bits.py
psychopy_crs/colorcal.py
psychopy_crs/optical.py
psychopy_crs/shaders.py
psychopy_crs-0.0.2.dist-info/LICENSE
psychopy_crs-0.0.2.dist-info/METADATA
psychopy_crs-0.0.2.dist-info/WHEEL
psychopy_crs-0.0.2.dist-info/top_level.txt
psychopy_crs-0.0.2.dist-info/RECORD
